core/__init__.py
core/agent.py
core/output_parser.py
core/splitter.py
core/structured_data_loader.py
core/unstructured_data_loader.py
core/web_crawler_loader.py
services/__init__.py
tests/__init__.py
tests/main_test.py
tests/structured_loader_test.py
tests/unstructured_loader_test.py
tests/test-files/insurance.pdf
tests/test-files/samplestructured1.xlsx
tests/test-files/samplestructured2.csv
tools/__init__.py
tools/ask_user.py
tools/recognize_loader.py
tools/write_config_file.py
docfusion-0.1.0.dist-info/LICENSE
docfusion-0.1.0.dist-info/METADATA
docfusion-0.1.0.dist-info/WHEEL
docfusion-0.1.0.dist-info/top_level.txt
docfusion-0.1.0.dist-info/RECORD
